qw/__init__.py
qw/__main__.py
qw/client.py
qw/conf.py
qw/decorators.py
qw/discovery.py
qw/exceptions.cpython-39-x86_64-linux-gnu.so
qw/process.py
qw/protocols.py
qw/server.py
qw/version.py
qw/bots/__init__.py
qw/bots/telegram.py
qw/broker/__init__.py
qw/broker/consumer.py
qw/broker/pickle.py
qw/broker/producer.py
qw/broker/rabbit.py
qw/executor/__init__.py
qw/queues/__init__.py
qw/queues/manager.py
qw/utils/__init__.py
qw/utils/events.py
qw/utils/functions.py
qw/utils/json.cpython-39-x86_64-linux-gnu.so
qw/utils/versions.py
qw/wrappers/__init__.py
qw/wrappers/base.py
qw/wrappers/di_task.py
qw/wrappers/func.py
resources/__init__.py
qworker-1.13.2.dist-info/LICENSE
qworker-1.13.2.dist-info/METADATA
qworker-1.13.2.dist-info/WHEEL
qworker-1.13.2.dist-info/entry_points.txt
qworker-1.13.2.dist-info/top_level.txt
qworker-1.13.2.dist-info/RECORD
