Metadata-Version: 2.1
Name: qworker
Version: 1.13.2
Summary: QueueWorker is asynchronous Task Queue implementation built on top of Asyncio.Can you spawn distributed workers to run functions inside workers.
Home-page: https://github.com/phenobarbital/qworker
Author: Jesus Lara
Author-email: jesuslara@phenobarbital.info
License: MIT
Project-URL: Source, https://github.com/phenobarbital/qworker
Project-URL: Funding, https://paypal.me/phenobarbital
Project-URL: Say Thanks!, https://saythanks.io/to/phenobarbital
Keywords: distributed objects,workers,asyncio,task queue,RPC,remote method call
Classifier: Development Status :: 4 - Beta
Classifier: Intended Audience :: Developers
Classifier: Intended Audience :: System Administrators
Classifier: Topic :: Software Development :: Libraries :: Python Modules
Classifier: Topic :: Software Development :: Build Tools
Classifier: Topic :: Software Development :: Object Brokering
Classifier: Topic :: System :: Distributed Computing
Classifier: Topic :: System :: Networking
Classifier: Operating System :: OS Independent
Classifier: Environment :: Web Environment
Classifier: Programming Language :: Python :: 3.8
Classifier: Programming Language :: Python :: 3.9
Classifier: Programming Language :: Python :: 3.10
Classifier: Programming Language :: Python :: 3.11
Classifier: Programming Language :: Python :: 3.12
Classifier: Framework :: AsyncIO
Requires-Python: >=3.8.0
License-File: LICENSE
Requires-Dist: asyncio==3.4.3
Requires-Dist: ciso8601>=2.2.0
Requires-Dist: navconfig[default,uvloop]>=1.7.9
Requires-Dist: asyncdb[default]>=2.9.0
Requires-Dist: async-notify[default]>=1.3.4
Requires-Dist: cloudpickle>=3.0.0
Requires-Dist: jsonpickle>=3.0.2
Requires-Dist: beautifulsoup4>=4.12.3
Requires-Dist: async-timeout==4.0.3
Requires-Dist: msgpack==1.1.0
Requires-Dist: aiormq==6.9.2
Requires-Dist: modin==0.32.0
Requires-Dist: dask[complete]==2024.8.2
Provides-Extra: tasks
Requires-Dist: flowtask>=5.8.20; extra == "tasks"
